oauth_userdb/__init__.py
oauth_userdb/client.py
oauth_userdb/dynamodb_client.py
oauth_userdb-1.0.5.dist-info/LICENSE
oauth_userdb-1.0.5.dist-info/METADATA
oauth_userdb-1.0.5.dist-info/WHEEL
oauth_userdb-1.0.5.dist-info/RECORD
